detachedproc/README.MD
detachedproc/__init__.py
detachedproc/requirements.txt
detachedproc/thirdparty.json
detachedproc-0.12.dist-info/LICENSE.rst
detachedproc-0.12.dist-info/METADATA
detachedproc-0.12.dist-info/WHEEL
detachedproc-0.12.dist-info/top_level.txt
detachedproc-0.12.dist-info/RECORD
