Metadata-Version: 2.1
Name: detachedproc
Version: 0.12
Summary: Similar to subprocess, but with 100% detached processes
Home-page: https://github.com/hansalemaos/detachedproc
Author: Johannes Fischer
Author-email: aulasparticularesdealemaosp@gmail.com
License: MIT
Keywords: detached,process,subprocess
Classifier: Development Status :: 4 - Beta
Classifier: Programming Language :: Python :: 3 :: Only
Classifier: Programming Language :: Python :: 3.10
Classifier: Topic :: Software Development :: Libraries :: Python Modules
Classifier: Topic :: Utilities
License-File: LICENSE.rst
Requires-Dist: kthread
Requires-Dist: kthread-sleep
Requires-Dist: psutil
Requires-Dist: shortpath83
Requires-Dist: touchtouch
Requires-Dist: what-os
